[{"place_id": 8667319, "licence": "Data \u00a9 OpenStreetMap contributors, ODbL 1.0. http://osm.org/copyright", "osm_type": "relation", "osm_id": 1846633, "lat": "-20.3028247", "lon": "-40.3006106", "class": "boundary", "type": "administrative", "place_rank": 20, "importance": 0.27501, "addresstype": "suburb", "name": "Santa L\u00facia", "display_name": "Santa L\u00facia, Vit\u00f3ria, Regi\u00e3o Geogr\u00e1fica Imediata de Vit\u00f3ria, Greater Vit\u00f3ria, Regi\u00e3o Geogr\u00e1fica Intermedi\u00e1ria de Vit\u00f3ria, Esp\u00edrito Santo, Southeast Region, Brazil", "boundingbox": ["-20.3113183", "-20.2934046", "-40.3047755", "-40.2955898"], "geojson": {"type": "Polygon", "coordinates": [[[-40.3047755, -20.294121], [-40.3037142, -20.3012305], [-40.3036378, -20.3017837], [-40.3024677, -20.3102533], [-40.3023308, -20.3113183], [-40.2979327, -20.3107015], [-40.2970448, -20.310557], [-40.2969513, -20.3105007], [-40.2964538, -20.3097844], [-40.2955898, -20.3086265], [-40.2979491, -20.3030072], [-40.2982264, -20.3023767], [-40.298459, -20.3017478], [-40.2990288, -20.3003538], [-40.2991169, -20.3001391], [-40.3013883, -20.2945964], [-40.3018642, -20.2934046], [-40.3040427, -20.2939428], [-40.3047755, -20.294121]]]}}, {"place_id": 9369318, "licence": "Data \u00a9 OpenStreetMap contributors, ODbL 1.0. http://osm.org/copyright", "osm_type": "node", "osm_id": 9191165183, "lat": "-19.9839195", "lon": "-40.5117642", "class": "place", "type": "hamlet", "place_rank": 20, "importance": 0.25000999999999995, "addresstype": "hamlet", "name": "Santa L\u00facia", "display_name": "Santa L\u00facia, Djalma Coutinho, Santa Leopoldina, Regi\u00e3o Geogr\u00e1fica Imediata de Afonso Cl\u00e1udio - Venda Nova do Imigrante - Santa Maria de Jetib\u00e1, Regi\u00e3o Geogr\u00e1fica Intermedi\u00e1ria de Vit\u00f3ria, Esp\u00edrito Santo, Southeast Region, Brazil", "boundingbox": ["-20.0039195", "-19.9639195", "-40.5317642", "-40.4917642"], "geojson": {"type": "Point", "coordinates": [-40.5117642, -19.9839195]}}]